mgitpy/ConfigProcessor.py
mgitpy/MultiGit.py
mgitpy/__init__.py
mgitpy/main.py
mgitpy/mgit.yaml
MGitPython-0.8.3.dist-info/LICENSE
MGitPython-0.8.3.dist-info/METADATA
MGitPython-0.8.3.dist-info/WHEEL
MGitPython-0.8.3.dist-info/entry_points.txt
MGitPython-0.8.3.dist-info/top_level.txt
MGitPython-0.8.3.dist-info/RECORD
