Metadata-Version: 2.1
Name: MGitPython
Version: 0.8.3
Summary: CLI tool to work with multiple git repositories.
Author-email: Włodzimierz Gajda <gajdaw@gajdaw.pl>
License: MIT
Keywords: cli,git,multiple,repo
Requires-Python: >=3.11
License-File: LICENSE
Requires-Dist: fire
Requires-Dist: jinja2
Requires-Dist: pyyaml
Requires-Dist: setuptools
